<PAMDataset>
  <Metadata>
    <MDI key="DataType">Generic</MDI>
  </Metadata>
  <PAMRasterBand band="1">
    <Description>Band_1</Description>
    <Histograms>
      <HistItem>
        <HistMin>2.531018708396005e-06</HistMin>
        <HistMax>4.159998893737793</HistMax>
        <BucketCount>256</BucketCount>
        <IncludeOutOfRange>1</IncludeOutOfRange>
        <Approximate>0</Approximate>
        <HistCounts>204|278|406|434|446|415|443|426|437|405|408|356|376|311|332|353|318|306|314|278|307|280|272|267|243|224|234|242|213|202|210|202|194|191|181|212|204|175|219|173|181|195|188|207|190|205|192|214|198|189|203|187|213|217|170|236|181|210|192|195|183|174|208|205|210|198|207|222|207|226|226|239|255|276|260|323|274|298|303|303|278|263|228|283|230|201|206|198|184|216|204|174|213|198|195|196|209|165|187|191|178|184|175|189|166|197|155|197|160|164|136|162|174|156|146|138|152|134|127|111|146|129|134|148|146|149|137|113|118|144|142|124|126|132|124|140|161|159|118|134|115|125|137|124|122|95|90|108|121|127|109|97|103|98|82|94|97|83|91|93|96|89|82|83|72|76|71|61|64|52|57|50|63|61|63|57|63|39|49|42|38|35|42|32|38|38|34|35|29|28|33|29|32|28|30|25|28|32|34|23|19|30|20|24|19|19|20|18|17|23|26|19|14|19|11|11|14|6|7|9|11|15|10|5|6|14|9|7|6|10|11|9|10|7|14|6|10|9|11|4|5|6|7|2|2|6|3|6|2|2|2|7|4|8|5|1</HistCounts>
      </HistItem>
    </Histograms>
    <Metadata>
      <MDI key="BandName">Band_1</MDI>
      <MDI key="RepresentationType">ATHEMATIC</MDI>
      <MDI key="STATISTICS_COVARIANCES">0.7611153912851297</MDI>
      <MDI key="STATISTICS_EXCLUDEDVALUES"></MDI>
      <MDI key="STATISTICS_MAXIMUM">4.1599988937378</MDI>
      <MDI key="STATISTICS_MEAN">1.2065423173962</MDI>
      <MDI key="STATISTICS_MINIMUM">2.531018708396e-06</MDI>
      <MDI key="STATISTICS_SKIPFACTORX">1</MDI>
      <MDI key="STATISTICS_SKIPFACTORY">1</MDI>
      <MDI key="STATISTICS_STDDEV">0.87241927493902</MDI>
    </Metadata>
  </PAMRasterBand>
</PAMDataset>
